easybrevo/__init__.py
easybrevo/core.py
easybrevo/settings.py
easybrevo/utils.py
easybrevo-0.1.2.dist-info/licenses/LICENSE
easybrevo-0.1.2.dist-info/METADATA
easybrevo-0.1.2.dist-info/WHEEL
easybrevo-0.1.2.dist-info/top_level.txt
easybrevo-0.1.2.dist-info/RECORD
