Metadata-Version: 2.4
Name: easybrevo
Version: 0.1.2
Summary: Use Brevo API with Python (the easy way)
Requires-Python: >=3.13
License-File: LICENSE
Requires-Dist: markdown>=3.8.2
Requires-Dist: prettyconf>=2.3.0
Requires-Dist: requests>=2.32.4
Dynamic: license-file
